limpyd_jobs/__init__.py
limpyd_jobs/models.py
limpyd_jobs/utils.py
limpyd_jobs/version.py
limpyd_jobs/workers.py
limpyd_jobs/scripts/__init__.py
limpyd_jobs/scripts/worker.py
redis_limpyd_jobs-2.dist-info/LICENSE
redis_limpyd_jobs-2.dist-info/METADATA
redis_limpyd_jobs-2.dist-info/WHEEL
redis_limpyd_jobs-2.dist-info/entry_points.txt
redis_limpyd_jobs-2.dist-info/top_level.txt
redis_limpyd_jobs-2.dist-info/zip-safe
redis_limpyd_jobs-2.dist-info/RECORD
