Metadata-Version: 2.1
Name: redis-limpyd-jobs
Version: 2
Summary: A queue/jobs system based on redis-limpyd, a redis orm (sort of) in python
Home-page: https://github.com/limpyd/redis-limpyd-jobs
Author: Stephane "Twidi" Angel
Author-email: s.angel@twidi.com
License: WTFPL
Keywords: redis,orm,jobs,queue
Platform: any
Classifier: Development Status :: 5 - Production/Stable
Classifier: Intended Audience :: Developers
Classifier: Operating System :: OS Independent
Classifier: Topic :: Software Development :: Libraries :: Python Modules
Classifier: Programming Language :: Python
Classifier: Programming Language :: Python :: 2
Classifier: Programming Language :: Python :: 2.7
Classifier: Programming Language :: Python :: 3
Classifier: Programming Language :: Python :: 3.5
Classifier: Programming Language :: Python :: 3.6
Classifier: Programming Language :: Python :: 3.7
Classifier: Programming Language :: Python :: 3.8
Classifier: Programming Language :: Python :: Implementation :: CPython
Classifier: Programming Language :: Python :: Implementation :: PyPy
Requires-Python: >=2.7, !=3.0.*, !=3.1.*, !=3.2.*, !=3.3.*, !=3.4.*
Requires-Dist: redis (>=3)
Requires-Dist: redis-limpyd (>=2)
Requires-Dist: redis-limpyd-extensions (>=2)
Requires-Dist: future
Requires-Dist: setproctitle
Requires-Dist: python-dateutil
